PytubeYoutube.py
pytubeyoutube-0.0.1.dist-info/WHEEL
pytubeyoutube-0.0.1.dist-info/METADATA
pytubeyoutube-0.0.1.dist-info/RECORD
